comet_mcp/__init__.py
comet_mcp/cache.py
comet_mcp/resources.py
comet_mcp/server.py
comet_mcp/session.py
comet_mcp/telemetry.py
comet_mcp/tool_loader.py
comet_mcp/tools.py
comet_mcp/utils.py
comet_mcp-1.3.0.dist-info/licenses/LICENSE
comet_mcp-1.3.0.dist-info/METADATA
comet_mcp-1.3.0.dist-info/WHEEL
comet_mcp-1.3.0.dist-info/entry_points.txt
comet_mcp-1.3.0.dist-info/top_level.txt
comet_mcp-1.3.0.dist-info/RECORD
