Metadata-Version: 2.4
Name: comet-mcp
Version: 1.3.0
Summary: MCP server for Comet ML API integration
License: Copyright (c) Comet ML, Inc
Project-URL: Homepage, https://github.com/comet-ml/comet-mcp
Project-URL: Repository, https://github.com/comet-ml/comet-mcp
Project-URL: Documentation, https://github.com/comet-ml/comet-mcp#readme
Project-URL: Bug Tracker, https://github.com/comet-ml/comet-mcp/issues
Keywords: comet,ml,mcp,model-context-protocol,machine-learning,experiment-tracking
Classifier: Development Status :: 4 - Beta
Classifier: Intended Audience :: Developers
Classifier: Intended Audience :: Science/Research
Classifier: License :: OSI Approved :: MIT License
Classifier: Operating System :: OS Independent
Classifier: Programming Language :: Python :: 3
Classifier: Programming Language :: Python :: 3.8
Classifier: Programming Language :: Python :: 3.9
Classifier: Programming Language :: Python :: 3.10
Classifier: Programming Language :: Python :: 3.11
Classifier: Programming Language :: Python :: 3.12
Classifier: Topic :: Scientific/Engineering :: Artificial Intelligence
Classifier: Topic :: Software Development :: Libraries :: Python Modules
Requires-Python: >=3.8
License-File: LICENSE
Requires-Dist: comet-ml>=3.0.0
Requires-Dist: fastapi>=0.100.0
Requires-Dist: mcp>=1.0.0
Requires-Dist: opentelemetry-api>=1.20.0
Requires-Dist: opentelemetry-exporter-otlp-proto-http>=1.20.0
Requires-Dist: opentelemetry-instrumentation>=0.42b0
Requires-Dist: opentelemetry-sdk>=1.20.0
Requires-Dist: requests>=2.25.0
Requires-Dist: uvicorn[standard]>=0.20.0
Provides-Extra: dev
Requires-Dist: pytest>=7.0.0; extra == "dev"
Requires-Dist: pytest-asyncio>=0.21.0; extra == "dev"
Dynamic: license-file
